setup.py
alnamkani_distributions/Binomialdistribution.py
alnamkani_distributions/Gaussiandistribution.py
alnamkani_distributions/Generaldistribution.py
alnamkani_distributions/__init__.py
alnamkani_distributions.egg-info/PKG-INFO
alnamkani_distributions.egg-info/SOURCES.txt
alnamkani_distributions.egg-info/dependency_links.txt
alnamkani_distributions.egg-info/not-zip-safe
alnamkani_distributions.egg-info/top_level.txt